cozo_embedded-0.7.6.dist-info/METADATA
cozo_embedded-0.7.6.dist-info/WHEEL
cozo_embedded.libs/libsqlite3-91742089.so.0
cozo_embedded/__init__.py
cozo_embedded/cozo_embedded.abi3.so
cozo_embedded-0.7.6.dist-info/RECORD
