Metadata-Version: 2.1
Name: cozo_embedded
Version: 0.7.6
Classifier: Topic :: Database
Classifier: Programming Language :: Rust
Classifier: Programming Language :: Python :: Implementation :: CPython
Classifier: Programming Language :: Python :: Implementation :: PyPy
Summary: Cozo database for python
Home-Page: https://www.cozodb.org
Author: Ziyang Hu
License: MPL-2.0
Requires-Python: >=3.7
Project-URL: Source Code, https://github.com/cozodb/cozo
